scoretracker
