Metadata-Version: 1.1
Name: GroupMeScoreTracker
Version: 1.6
Summary: A score tracker for GroupMe, allowing competition between friends
Home-page: https://github.com/cheeseypi/GroupMeScoreTracker
Author: Matthew Doto
Author-email: matt@mattdoto.com
License: LICENSE.txt
Download-URL: https://github.com/cheeseypi/GroupMeScoreTracker/archive/v1.6.tar.gz
Platform: UNKNOWN
